{
  "environments" : [
    {
      "name": "url-with-delimitter",
      "domain": "http://localhost:4300",
      "versioningScheme": "url",
      "contexts": [
        {
          "name": "url-with-delimitter",
          "domain": "http://localhost:4300",
          "versioningScheme": "url",
          "endpoints": [
            {
              "resource": "url-with-delimitter",
              "url": "http://localhost",
              "versions": [
                {
                  "verb": "GET",
                  "value": "v1"
                }
              ]
            }
          ]
        }
      ]
    }
  ],
  "contexts": [],
  "resourceEnvironment": "url-with-delimitter"
}
